oolearning
tests
