Metadata-Version: 1.1
Name: oolearning
Version: 0.3.3
Summary: A simple machine learning library based on Object Oriented design principles.
Home-page: https://github.com/shane-kercheval/oo-learning
Author: Shane Kercheval
Author-email: shane.kercheval@gmail.com
License: MIT
Download-URL: https://github.com/shane-kercheval/oo-learning/archive/0.3.3.tar.gz
Keywords: machine-learning,data-science,object-oriented-programming,data-analysis
Platform: UNKNOWN
Classifier: Development Status :: 3 - Alpha
Classifier: Programming Language :: Python :: 3
